{
  "auto_restart_backend": true,
  "start_backend_on_launch": false,
  "hide_to_tray_on_close": true,
  "launch_manager_on_startup": false,
  "enable_health_check": true,
  "frontend_deploy_source": "",
  "release_package_path": "",
  "backup_dir": "D:\\FinFlow\\backups",
  "sqlcmd_path": "sqlcmd",
  "git_repo_url": "https://github.com/guonc945/FinFlow",
  "git_branch": "main",
  "backup_retention_days": "30",
  "backup_retention_count": "10",
  "log_max_size_mb": "20",
  "log_archive_retention_days": "90",
  "webhook_url": ""
}